{
  "project_info": {
    "project_number": "1010655508709",
    "project_id": "mini-recipe-book",
    "storage_bucket": "mini-recipe-book.firebasestorage.app"
  },
  "client": [
    {
      "client_info": {
        "mobilesdk_app_id": "1:1010655508709:android:9690f892d2b40d2a23bc0c",
        "android_client_info": {
          "package_name": "com.example.midterm2"
        }
      },
      "oauth_client": [],
      "api_key": [
        {
          "current_key": "AIzaSyAiqu4wqGO5GchgmBhDaebB5SbDfEDqmrQ"
        }
      ],
      "services": {
        "appinvite_service": {
          "other_platform_oauth_client": []
        }
      }
    }
  ],
  "configuration_version": "1"
}